Metadata-Version: 2.1
Name: audformat
Version: 1.3.1
Summary: Python implementation of audformat
Author: Johannes Wagner, BahaEddine Abrougui
Author-email: Hagen Wierstorf <hwierstorf@audeering.com>, Christian Geng <cgeng@audeering.com>
License: MIT License
Project-URL: repository, https://github.com/audeering/audformat/
Project-URL: documentation, https://audeering.github.io/audformat/
Keywords: audio,database,annotation
Classifier: Development Status :: 5 - Production/Stable
Classifier: Intended Audience :: Science/Research
Classifier: Intended Audience :: Developers
Classifier: License :: OSI Approved :: MIT License
Classifier: Operating System :: OS Independent
Classifier: Programming Language :: Python
Classifier: Programming Language :: Python :: 3
Classifier: Programming Language :: Python :: 3.9
Classifier: Programming Language :: Python :: 3.10
Classifier: Programming Language :: Python :: 3.11
Classifier: Topic :: Scientific/Engineering
Requires-Python: >=3.9
License-File: LICENSE
Requires-Dist: audeer>=2.0.0
Requires-Dist: audiofile>=0.4.0
Requires-Dist: iso639-lang
Requires-Dist: iso3166
Requires-Dist: oyaml
Requires-Dist: pandas>=2.1.0
Requires-Dist: pyarrow>=10.0.1
Requires-Dist: pyyaml>=5.4.1
